{
  "教学楼": [
    {
      "name": "慧源楼",
      "coordinates": [115.804362, 28.663298],
      "priority": 2,
      "id": 0,
      "info": "慧源楼，又名主教，小名果汁楼，共5层，是本科生上公共课（如高等数学，中国近现代史纲要等）的主要环形教学楼。教室号由大门进入后顺时针依次递增。",
      "functions": [
        "本科生公共课程学习的主要场所；自习；大部分科目期末考试考场；英语四六级分考场等。"
      ],
      "offices": [],
      "activities": [
        "周末影展：每周五周六晚，在慧源楼244的观影活动，播放经典高分影片，由南昌大学心理健康发展协会与南昌大学学生会主办。"
      ],
      "tips": {
        "info": [],
        "functions": [
          {
            "title": "自习规则：",
            "content": [
              "专门的自习室实行平台预约制：可点击南大家园“生活板块”中的自习预约进行操作。",
              "楼道等公共空间内的桌椅可随意使用。"
            ]
          }
        ],
        "offices": [],
        "activities": [
          {
            "title": "慧源楼244心灵影展观影需知：",
            "content": [
              "①南昌大学学生心理健康发展协会心灵影展定于每周五晚6：30为大家播放心理影片。为了方便影院管理以及避免座位不足的问题，我们向学习通开放了100个预约名额，对本群开放了160个预约名额。大家自选预约渠道，不需要重复预约。届时大家在进入影厅之前会有工作人员核实大家预约信息才让大家进入影厅观影。大家在观影前务必及时预约。名额有限，先到先得哦☺️☺️☺️！",
              "②到场后在座位的第一排右侧有预约二维码，通过其他渠道（比如慧源楼大厅电子屏）在学习通预约了座位，到场后请到第一排扫码签到🌷！",
              "③如遇到预约无法到场或相关预约扫码签到问题，请大家咨询相关负责中心和社团。这不属于心协的负责范畴😘。",
              "④影厅原则上不能携带食物入场，如大家需要记得离场前清理自己遗留的垃圾。",
              "最后，欢迎大家每周五晚来参加我们的心灵影展！影片结束后我们会给大家分享影片中的心理学看点，同时参与互动的同学也会有小礼品赠送哦❤️❤️❤️👏👏👏！"
            ]
          }
        ]
      }
    },
    {
      "name": "信工楼",
      "coordinates": [115.797684, 28.658021],
      "priority": 2,
      "id": 1,
      "info": "慧源楼，又名主教，小名果汁楼，共5层，是本科生上公共课（如高等数学，中国近现代史纲要等）的主要环形教学楼。教室号由大门进入后顺时针依次递增。",
      "functions": [
        "本科生公共课程学习的主要场所；自习；大部分科目期末考试考场；英语四六级分考场等。"
      ],
      "offices": [],
      "activities": [
        "周末影展：每周五周六晚，在慧源楼244的观影活动，播放经典高分影片，由南昌大学心理健康发展协会与南昌大学学生会主办。"
      ],
      "tips": {
        "info": [],
        "functions": [],
        "offices": [],
        "activities": []
      }
    },
    {
      "name": "文法楼",
      "coordinates": [115.804576, 28.660339],
      "priority": 6,
      "id": 2,
      "info": "慧源楼，又名主教，小名果汁楼，共5层，是本科生上公共课（如高等数学，中国近现代史纲要等）的主要环形教学楼。教室号由大门进入后顺时针依次递增。",
      "functions": [
        "本科生公共课程学习的主要场所；自习；大部分科目期末考试考场；英语四六级分考场等。"
      ],
      "offices": [],
      "activities": [
        "周末影展：每周五周六晚，在慧源楼244的观影活动，播放经典高分影片，由南昌大学心理健康发展协会与南昌大学学生会主办。"
      ],
      "tips": {
        "info": [],
        "functions": [],
        "offices": [],
        "activities": []
      }
    },
    {
      "name": "智华楼",
      "coordinates": [115.804362, 28.663298],
      "priority": 6,
      "id": 3,
      "info": "慧源楼，又名主教，小名果汁楼，共5层，是本科生上公共课（如高等数学，中国近现代史纲要等）的主要环形教学楼。教室号由大门进入后顺时针依次递增。",
      "functions": [
        "本科生公共课程学习的主要场所；自习；大部分科目期末考试考场；英语四六级分考场等。"
      ],
      "offices": [],
      "activities": [
        "周末影展：每周五周六晚，在慧源楼244的观影活动，播放经典高分影片，由南昌大学心理健康发展协会与南昌大学学生会主办。"
      ],
      "tips": {
        "info": [],
        "functions": [],
        "offices": [],
        "activities": []
      }
    },
    {
      "name": "理生楼",
      "coordinates": [115.804362, 28.663298],
      "priority": 6,
      "id": 4,
      "info": "慧源楼，又名主教，小名果汁楼，共5层，是本科生上公共课（如高等数学，中国近现代史纲要等）的主要环形教学楼。教室号由大门进入后顺时针依次递增。",
      "functions": [
        "本科生公共课程学习的主要场所；自习；大部分科目期末考试考场；英语四六级分考场等。"
      ],
      "offices": [],
      "activities": [
        "周末影展：每周五周六晚，在慧源楼244的观影活动，播放经典高分影片，由南昌大学心理健康发展协会与南昌大学学生会主办。"
      ],
      "tips": {
        "info": [],
        "functions": [],
        "offices": [],
        "activities": []
      }
    },
    {
      "name": "基础实验大楼",
      "coordinates": [115.804362, 28.663298],
      "priority": 6,
      "id": 5,
      "info": "慧源楼，又名主教，小名果汁楼，共5层，是本科生上公共课（如高等数学，中国近现代史纲要等）的主要环形教学楼。教室号由大门进入后顺时针依次递增。",
      "functions": [
        "本科生公共课程学习的主要场所；自习；大部分科目期末考试考场；英语四六级分考场等。"
      ],
      "offices": [],
      "activities": [
        "周末影展：每周五周六晚，在慧源楼244的观影活动，播放经典高分影片，由南昌大学心理健康发展协会与南昌大学学生会主办。"
      ],
      "tips": {
        "info": [],
        "functions": [],
        "offices": [],
        "activities": []
      }
    },
    {
      "name": "艺术楼",
      "coordinates": [115.804362, 28.663298],
      "priority": 6,
      "id": 6,
      "info": "慧源楼，又名主教，小名果汁楼，共5层，是本科生上公共课（如高等数学，中国近现代史纲要等）的主要环形教学楼。教室号由大门进入后顺时针依次递增。",
      "functions": [
        "本科生公共课程学习的主要场所；自习；大部分科目期末考试考场；英语四六级分考场等。"
      ],
      "offices": [],
      "activities": [
        "周末影展：每周五周六晚，在慧源楼244的观影活动，播放经典高分影片，由南昌大学心理健康发展协会与南昌大学学生会主办。"
      ],
      "tips": {
        "info": [],
        "functions": [],
        "offices": [],
        "activities": []
      }
    },
    {
      "name": "建工楼",
      "coordinates": [115.804362, 28.663298],
      "priority": 6,
      "id": 7,
      "info": "慧源楼，又名主教，小名果汁楼，共5层，是本科生上公共课（如高等数学，中国近现代史纲要等）的主要环形教学楼。教室号由大门进入后顺时针依次递增。",
      "functions": [
        "本科生公共课程学习的主要场所；自习；大部分科目期末考试考场；英语四六级分考场等。"
      ],
      "offices": [],
      "activities": [
        "周末影展：每周五周六晚，在慧源楼244的观影活动，播放经典高分影片，由南昌大学心理健康发展协会与南昌大学学生会主办。"
      ],
      "tips": {
        "info": [],
        "functions": [],
        "offices": [],
        "activities": []
      }
    },
    {
      "name": "外经楼",
      "coordinates": [115.804362, 28.663298],
      "priority": 6,
      "id": 8,
      "info": "慧源楼，又名主教，小名果汁楼，共5层，是本科生上公共课（如高等数学，中国近现代史纲要等）的主要环形教学楼。教室号由大门进入后顺时针依次递增。",
      "functions": [
        "本科生公共课程学习的主要场所；自习；大部分科目期末考试考场；英语四六级分考场等。"
      ],
      "offices": [],
      "activities": [
        "周末影展：每周五周六晚，在慧源楼244的观影活动，播放经典高分影片，由南昌大学心理健康发展协会与南昌大学学生会主办。"
      ],
      "tips": {
        "info": [],
        "functions": [],
        "offices": [],
        "activities": []
      }
    },
    {
      "name": "环境楼",
      "coordinates": [115.804362, 28.663298],
      "priority": 6,
      "id": 9,
      "info": "慧源楼，又名主教，小名果汁楼，共5层，是本科生上公共课（如高等数学，中国近现代史纲要等）的主要环形教学楼。教室号由大门进入后顺时针依次递增。",
      "functions": [
        "本科生公共课程学习的主要场所；自习；大部分科目期末考试考场；英语四六级分考场等。"
      ],
      "offices": [],
      "activities": [
        "周末影展：每周五周六晚，在慧源楼244的观影活动，播放经典高分影片，由南昌大学心理健康发展协会与南昌大学学生会主办。"
      ],
      "tips": {
        "info": [],
        "functions": [],
        "offices": [],
        "activities": []
      }
    }
  ],
  "体育场所": [
    {
      "name": "体育馆",
      "coordinates": [115.804362, 28.663298],
      "priority": 2,
      "id": 0,
      "info": "慧源楼，又名主教，小名果汁楼，共5层，是本科生上公共课（如高等数学，中国近现代史纲要等）的主要环形教学楼。教室号由大门进入后顺时针依次递增。",
      "functions": [
        "本科生公共课程学习的主要场所；自习；大部分科目期末考试考场；英语四六级分考场等。"
      ],
      "offices": [],
      "activities": [
        "周末影展：每周五周六晚，在慧源楼244的观影活动，播放经典高分影片，由南昌大学心理健康发展协会与南昌大学学生会主办。"
      ],
      "tips": {
        "info": [],
        "functions": [],
        "offices": [],
        "activities": []
      }
    },
    {
      "name": "羽毛球/网球馆",
      "coordinates": [115.804362, 28.663298],
      "priority": 2,
      "id": 1,
      "info": "慧源楼，又名主教，小名果汁楼，共5层，是本科生上公共课（如高等数学，中国近现代史纲要等）的主要环形教学楼。教室号由大门进入后顺时针依次递增。",
      "functions": [
        "本科生公共课程学习的主要场所；自习；大部分科目期末考试考场；英语四六级分考场等。"
      ],
      "offices": [],
      "activities": [
        "周末影展：每周五周六晚，在慧源楼244的观影活动，播放经典高分影片，由南昌大学心理健康发展协会与南昌大学学生会主办。"
      ],
      "tips": {
        "info": [],
        "functions": [],
        "offices": [],
        "activities": []
      }
    },
    {
      "name": "游泳馆",
      "coordinates": [115.804362, 28.663298],
      "priority": 2,
      "id": 2,
      "info": "慧源楼，又名主教，小名果汁楼，共5层，是本科生上公共课（如高等数学，中国近现代史纲要等）的主要环形教学楼。教室号由大门进入后顺时针依次递增。",
      "functions": [
        "本科生公共课程学习的主要场所；自习；大部分科目期末考试考场；英语四六级分考场等。"
      ],
      "offices": [],
      "activities": [
        "周末影展：每周五周六晚，在慧源楼244的观影活动，播放经典高分影片，由南昌大学心理健康发展协会与南昌大学学生会主办。"
      ],
      "tips": {
        "info": [],
        "functions": [],
        "offices": [],
        "activities": []
      }
    },
    {
      "name": "白帆运动场",
      "coordinates": [115.804362, 28.663298],
      "priority": 2,
      "id": 3,
      "info": "慧源楼，又名主教，小名果汁楼，共5层，是本科生上公共课（如高等数学，中国近现代史纲要等）的主要环形教学楼。教室号由大门进入后顺时针依次递增。",
      "functions": [
        "本科生公共课程学习的主要场所；自习；大部分科目期末考试考场；英语四六级分考场等。"
      ],
      "offices": [],
      "activities": [
        "周末影展：每周五周六晚，在慧源楼244的观影活动，播放经典高分影片，由南昌大学心理健康发展协会与南昌大学学生会主办。"
      ],
      "tips": {
        "info": [],
        "functions": [],
        "offices": [],
        "activities": []
      }
    },
    {
      "name": "修贤运动场",
      "coordinates": [115.804362, 28.663298],
      "priority": 2,
      "id": 4,
      "info": "慧源楼，又名主教，小名果汁楼，共5层，是本科生上公共课（如高等数学，中国近现代史纲要等）的主要环形教学楼。教室号由大门进入后顺时针依次递增。",
      "functions": [
        "本科生公共课程学习的主要场所；自习；大部分科目期末考试考场；英语四六级分考场等。"
      ],
      "offices": [],
      "activities": [
        "周末影展：每周五周六晚，在慧源楼244的观影活动，播放经典高分影片，由南昌大学心理健康发展协会与南昌大学学生会主办。"
      ],
      "tips": {
        "info": [],
        "functions": [],
        "offices": [],
        "activities": []
      }
    },
    {
      "name": "天健运动场",
      "coordinates": [115.804362, 28.663298],
      "priority": 2,
      "id": 5,
      "info": "慧源楼，又名主教，小名果汁楼，共5层，是本科生上公共课（如高等数学，中国近现代史纲要等）的主要环形教学楼。教室号由大门进入后顺时针依次递增。",
      "functions": [
        "本科生公共课程学习的主要场所；自习；大部分科目期末考试考场；英语四六级分考场等。"
      ],
      "offices": [],
      "activities": [
        "周末影展：每周五周六晚，在慧源楼244的观影活动，播放经典高分影片，由南昌大学心理健康发展协会与南昌大学学生会主办。"
      ],
      "tips": {
        "info": [],
        "functions": [],
        "offices": [],
        "activities": []
      }
    }
  ],
  "生活": [
    {
      "name": "校医院",
      "coordinates": [115.804362, 28.663298],
      "priority": 2,
      "id": 0,
      "info": "慧源楼，又名主教，小名果汁楼，共5层，是本科生上公共课（如高等数学，中国近现代史纲要等）的主要环形教学楼。教室号由大门进入后顺时针依次递增。",
      "functions": [
        "本科生公共课程学习的主要场所；自习；大部分科目期末考试考场；英语四六级分考场等。"
      ],
      "offices": [],
      "activities": [
        "周末影展：每周五周六晚，在慧源楼244的观影活动，播放经典高分影片，由南昌大学心理健康发展协会与南昌大学学生会主办。"
      ],
      "tips": {
        "info": [],
        "functions": [],
        "offices": [],
        "activities": []
      }
    },
    {
      "name": "修贤快递点",
      "coordinates": [115.804362, 28.663298],
      "priority": 2,
      "id": 1,
      "info": "慧源楼，又名主教，小名果汁楼，共5层，是本科生上公共课（如高等数学，中国近现代史纲要等）的主要环形教学楼。教室号由大门进入后顺时针依次递增。",
      "functions": [
        "本科生公共课程学习的主要场所；自习；大部分科目期末考试考场；英语四六级分考场等。"
      ],
      "offices": [],
      "activities": [
        "周末影展：每周五周六晚，在慧源楼244的观影活动，播放经典高分影片，由南昌大学心理健康发展协会与南昌大学学生会主办。"
      ],
      "tips": {
        "info": [],
        "functions": [],
        "offices": [],
        "activities": []
      }
    },
    {
      "name": "天健快递点",
      "coordinates": [115.804362, 28.663298],
      "priority": 2,
      "id": 2,
      "info": "慧源楼，又名主教，小名果汁楼，共5层，是本科生上公共课（如高等数学，中国近现代史纲要等）的主要环形教学楼。教室号由大门进入后顺时针依次递增。",
      "functions": [
        "本科生公共课程学习的主要场所；自习；大部分科目期末考试考场；英语四六级分考场等。"
      ],
      "offices": [],
      "activities": [
        "周末影展：每周五周六晚，在慧源楼244的观影活动，播放经典高分影片，由南昌大学心理健康发展协会与南昌大学学生会主办。"
      ],
      "tips": {
        "info": [],
        "functions": [],
        "offices": [],
        "activities": []
      }
    },
    {
      "name": "一二食堂",
      "coordinates": [115.804362, 28.663298],
      "priority": 2,
      "id": 3,
      "info": "慧源楼，又名主教，小名果汁楼，共5层，是本科生上公共课（如高等数学，中国近现代史纲要等）的主要环形教学楼。教室号由大门进入后顺时针依次递增。",
      "functions": [
        "本科生公共课程学习的主要场所；自习；大部分科目期末考试考场；英语四六级分考场等。"
      ],
      "offices": [],
      "activities": [
        "周末影展：每周五周六晚，在慧源楼244的观影活动，播放经典高分影片，由南昌大学心理健康发展协会与南昌大学学生会主办。"
      ],
      "tips": {
        "info": [],
        "functions": [],
        "offices": [],
        "activities": []
      }
    },
    {
      "name": "三四食堂",
      "coordinates": [115.804362, 28.663298],
      "priority": 2,
      "id": 4,
      "info": "慧源楼，又名主教，小名果汁楼，共5层，是本科生上公共课（如高等数学，中国近现代史纲要等）的主要环形教学楼。教室号由大门进入后顺时针依次递增。",
      "functions": [
        "本科生公共课程学习的主要场所；自习；大部分科目期末考试考场；英语四六级分考场等。"
      ],
      "offices": [],
      "activities": [
        "周末影展：每周五周六晚，在慧源楼244的观影活动，播放经典高分影片，由南昌大学心理健康发展协会与南昌大学学生会主办。"
      ],
      "tips": {
        "info": [],
        "functions": [],
        "offices": [],
        "activities": []
      }
    },
    {
      "name": "六七食堂",
      "coordinates": [115.804362, 28.663298],
      "priority": 2,
      "id": 5,
      "info": "慧源楼，又名主教，小名果汁楼，共5层，是本科生上公共课（如高等数学，中国近现代史纲要等）的主要环形教学楼。教室号由大门进入后顺时针依次递增。",
      "functions": [
        "本科生公共课程学习的主要场所；自习；大部分科目期末考试考场；英语四六级分考场等。"
      ],
      "offices": [],
      "activities": [
        "周末影展：每周五周六晚，在慧源楼244的观影活动，播放经典高分影片，由南昌大学心理健康发展协会与南昌大学学生会主办。"
      ],
      "tips": {
        "info": [],
        "functions": [],
        "offices": [],
        "activities": []
      }
    },
    {
      "name": "九十食堂",
      "coordinates": [115.804362, 28.663298],
      "priority": 2,
      "id": 6,
      "info": "慧源楼，又名主教，小名果汁楼，共5层，是本科生上公共课（如高等数学，中国近现代史纲要等）的主要环形教学楼。教室号由大门进入后顺时针依次递增。",
      "functions": [
        "本科生公共课程学习的主要场所；自习；大部分科目期末考试考场；英语四六级分考场等。"
      ],
      "offices": [],
      "activities": [
        "周末影展：每周五周六晚，在慧源楼244的观影活动，播放经典高分影片，由南昌大学心理健康发展协会与南昌大学学生会主办。"
      ],
      "tips": {
        "info": [],
        "functions": [],
        "offices": [],
        "activities": []
      }
    },
    {
      "name": "修贤宿舍",
      "coordinates": [115.804362, 28.663298],
      "priority": 2,
      "id": 7,
      "info": "慧源楼，又名主教，小名果汁楼，共5层，是本科生上公共课（如高等数学，中国近现代史纲要等）的主要环形教学楼。教室号由大门进入后顺时针依次递增。",
      "functions": [
        "本科生公共课程学习的主要场所；自习；大部分科目期末考试考场；英语四六级分考场等。"
      ],
      "offices": [],
      "activities": [
        "周末影展：每周五周六晚，在慧源楼244的观影活动，播放经典高分影片，由南昌大学心理健康发展协会与南昌大学学生会主办。"
      ],
      "tips": {
        "info": [],
        "functions": [],
        "offices": [],
        "activities": []
      }
    },
    {
      "name": "天健宿舍",
      "coordinates": [115.804362, 28.663298],
      "priority": 2,
      "id": 8,
      "info": "慧源楼，又名主教，小名果汁楼，共5层，是本科生上公共课（如高等数学，中国近现代史纲要等）的主要环形教学楼。教室号由大门进入后顺时针依次递增。",
      "functions": [
        "本科生公共课程学习的主要场所；自习；大部分科目期末考试考场；英语四六级分考场等。"
      ],
      "offices": [],
      "activities": [
        "周末影展：每周五周六晚，在慧源楼244的观影活动，播放经典高分影片，由南昌大学心理健康发展协会与南昌大学学生会主办。"
      ],
      "tips": {
        "info": [],
        "functions": [],
        "offices": [],
        "activities": []
      }
    },
    {
      "name": "慧源宿舍",
      "coordinates": [115.804362, 28.663298],
      "priority": 2,
      "id": 9,
      "info": "慧源楼，又名主教，小名果汁楼，共5层，是本科生上公共课（如高等数学，中国近现代史纲要等）的主要环形教学楼。教室号由大门进入后顺时针依次递增。",
      "functions": [
        "本科生公共课程学习的主要场所；自习；大部分科目期末考试考场；英语四六级分考场等。"
      ],
      "offices": [],
      "activities": [
        "周末影展：每周五周六晚，在慧源楼244的观影活动，播放经典高分影片，由南昌大学心理健康发展协会与南昌大学学生会主办。"
      ],
      "tips": {
        "info": [],
        "functions": [],
        "offices": [],
        "activities": []
      }
    }
  ],
  "自然景观": [
    {
      "name": "先骕园",
      "coordinates": [115.804362, 28.663298],
      "priority": 2,
      "id": 0,
      "info": "慧源楼，又名主教，小名果汁楼，共5层，是本科生上公共课（如高等数学，中国近现代史纲要等）的主要环形教学楼。教室号由大门进入后顺时针依次递增。",
      "functions": [
        "本科生公共课程学习的主要场所；自习；大部分科目期末考试考场；英语四六级分考场等。"
      ],
      "offices": [],
      "activities": [
        "周末影展：每周五周六晚，在慧源楼244的观影活动，播放经典高分影片，由南昌大学心理健康发展协会与南昌大学学生会主办。"
      ],
      "tips": {
        "info": [],
        "functions": [],
        "offices": [],
        "activities": []
      }
    },
    {
      "name": "孔雀园",
      "coordinates": [115.804362, 28.663298],
      "priority": 2,
      "id": 1,
      "info": "慧源楼，又名主教，小名果汁楼，共5层，是本科生上公共课（如高等数学，中国近现代史纲要等）的主要环形教学楼。教室号由大门进入后顺时针依次递增。",
      "functions": [
        "本科生公共课程学习的主要场所；自习；大部分科目期末考试考场；英语四六级分考场等。"
      ],
      "offices": [],
      "activities": [
        "周末影展：每周五周六晚，在慧源楼244的观影活动，播放经典高分影片，由南昌大学心理健康发展协会与南昌大学学生会主办。"
      ],
      "tips": {
        "info": [],
        "functions": [],
        "offices": [],
        "activities": []
      }
    },
    {
      "name": "正气广场",
      "coordinates": [115.804362, 28.663298],
      "priority": 2,
      "id": 2,
      "info": "慧源楼，又名主教，小名果汁楼，共5层，是本科生上公共课（如高等数学，中国近现代史纲要等）的主要环形教学楼。教室号由大门进入后顺时针依次递增。",
      "functions": [
        "本科生公共课程学习的主要场所；自习；大部分科目期末考试考场；英语四六级分考场等。"
      ],
      "offices": [],
      "activities": [
        "周末影展：每周五周六晚，在慧源楼244的观影活动，播放经典高分影片，由南昌大学心理健康发展协会与南昌大学学生会主办。"
      ],
      "tips": {
        "info": [],
        "functions": [],
        "offices": [],
        "activities": []
      }
    },
    {
      "name": "树人广场",
      "coordinates": [115.804362, 28.663298],
      "priority": 2,
      "id": 3,
      "info": "慧源楼，又名主教，小名果汁楼，共5层，是本科生上公共课（如高等数学，中国近现代史纲要等）的主要环形教学楼。教室号由大门进入后顺时针依次递增。",
      "functions": [
        "本科生公共课程学习的主要场所；自习；大部分科目期末考试考场；英语四六级分考场等。"
      ],
      "offices": [],
      "activities": [
        "周末影展：每周五周六晚，在慧源楼244的观影活动，播放经典高分影片，由南昌大学心理健康发展协会与南昌大学学生会主办。"
      ],
      "tips": {
        "info": [],
        "functions": [],
        "offices": [],
        "activities": []
      }
    }
  ],
  "其他": [
    {
      "name": "图书馆",
      "coordinates": [115.804362, 28.663298],
      "priority": 2,
      "id": 0,
      "info": "慧源楼，又名主教，小名果汁楼，共5层，是本科生上公共课（如高等数学，中国近现代史纲要等）的主要环形教学楼。教室号由大门进入后顺时针依次递增。",
      "functions": [
        "本科生公共课程学习的主要场所；自习；大部分科目期末考试考场；英语四六级分考场等。"
      ],
      "offices": [],
      "activities": [
        "周末影展：每周五周六晚，在慧源楼244的观影活动，播放经典高分影片，由南昌大学心理健康发展协会与南昌大学学生会主办。"
      ],
      "tips": {
        "info": [],
        "functions": [],
        "offices": [],
        "activities": []
      }
    },
    {
      "name": "音乐厅",
      "coordinates": [115.804362, 28.663298],
      "priority": 2,
      "id": 1,
      "info": "慧源楼，又名主教，小名果汁楼，共5层，是本科生上公共课（如高等数学，中国近现代史纲要等）的主要环形教学楼。教室号由大门进入后顺时针依次递增。",
      "functions": [
        "本科生公共课程学习的主要场所；自习；大部分科目期末考试考场；英语四六级分考场等。"
      ],
      "offices": [],
      "activities": [
        "周末影展：每周五周六晚，在慧源楼244的观影活动，播放经典高分影片，由南昌大学心理健康发展协会与南昌大学学生会主办。"
      ],
      "tips": {
        "info": [],
        "functions": [],
        "offices": [],
        "activities": []
      }
    },
    {
      "name": "一号门",
      "coordinates": [115.804362, 28.663298],
      "priority": 2,
      "id": 2,
      "info": "慧源楼，又名主教，小名果汁楼，共5层，是本科生上公共课（如高等数学，中国近现代史纲要等）的主要环形教学楼。教室号由大门进入后顺时针依次递增。",
      "functions": [
        "本科生公共课程学习的主要场所；自习；大部分科目期末考试考场；英语四六级分考场等。"
      ],
      "offices": [],
      "activities": [
        "周末影展：每周五周六晚，在慧源楼244的观影活动，播放经典高分影片，由南昌大学心理健康发展协会与南昌大学学生会主办。"
      ],
      "tips": {
        "info": [],
        "functions": [],
        "offices": [],
        "activities": []
      }
    },
    {
      "name": "二号门",
      "coordinates": [115.804362, 28.663298],
      "priority": 2,
      "id": 3,
      "info": "慧源楼，又名主教，小名果汁楼，共5层，是本科生上公共课（如高等数学，中国近现代史纲要等）的主要环形教学楼。教室号由大门进入后顺时针依次递增。",
      "functions": [
        "本科生公共课程学习的主要场所；自习；大部分科目期末考试考场；英语四六级分考场等。"
      ],
      "offices": [],
      "activities": [
        "周末影展：每周五周六晚，在慧源楼244的观影活动，播放经典高分影片，由南昌大学心理健康发展协会与南昌大学学生会主办。"
      ],
      "tips": {
        "info": [],
        "functions": [],
        "offices": [],
        "activities": []
      }
    },
    {
      "name": "三号门",
      "coordinates": [115.804362, 28.663298],
      "priority": 2,
      "id": 4,
      "info": "慧源楼，又名主教，小名果汁楼，共5层，是本科生上公共课（如高等数学，中国近现代史纲要等）的主要环形教学楼。教室号由大门进入后顺时针依次递增。",
      "functions": [
        "本科生公共课程学习的主要场所；自习；大部分科目期末考试考场；英语四六级分考场等。"
      ],
      "offices": [],
      "activities": [
        "周末影展：每周五周六晚，在慧源楼244的观影活动，播放经典高分影片，由南昌大学心理健康发展协会与南昌大学学生会主办。"
      ],
      "tips": {
        "info": [],
        "functions": [],
        "offices": [],
        "activities": []
      }
    },
    {
      "name": "四号门",
      "coordinates": [115.804362, 28.663298],
      "priority": 2,
      "id": 5,
      "info": "慧源楼，又名主教，小名果汁楼，共5层，是本科生上公共课（如高等数学，中国近现代史纲要等）的主要环形教学楼。教室号由大门进入后顺时针依次递增。",
      "functions": [
        "本科生公共课程学习的主要场所；自习；大部分科目期末考试考场；英语四六级分考场等。"
      ],
      "offices": [],
      "activities": [
        "周末影展：每周五周六晚，在慧源楼244的观影活动，播放经典高分影片，由南昌大学心理健康发展协会与南昌大学学生会主办。"
      ],
      "tips": {
        "info": [],
        "functions": [],
        "offices": [],
        "activities": []
      }
    }
  ]
}
